{
 "attempt": 0,
 "end-status": 3,
 "end-time": "1689775475430636-2023-07-19-14:04:35:430.636",
 "events": [
  {
   "code": 7,
   "coordinates": {
    "ego": [
     0.0,
     0.0,
     0.1
    ],
    "end": [
     0.0,
     0.0,
     0.1
    ]
   },
   "description": "Moving started ",
   "timestamp": "1689775472864165-2023-07-19-14:04:32:864.165",
   "x": 0.0,
   "y": 0.0
  },
  {
   "code": 7,
   "coordinates": {
    "ego": [
     0.0,
     0.0,
     0.1
    ],
    "end": [
     0.08,
     0.0,
     0.1
    ]
   },
   "description": "Moving started ",
   "timestamp": "1689775472874087-2023-07-19-14:04:32:874.87",
   "x": 0.0,
   "y": 0.0
  },
  {
   "code": 7,
   "coordinates": {
    "ego": [
     0.08,
     0.0,
     0.1
    ],
    "end": [
     0.198,
     -0.018000000000000002,
     0.1
    ]
   },
   "description": "Moving started ",
   "timestamp": "1689775472888291-2023-07-19-14:04:32:888.291",
   "x": 0.08,
   "y": 0.0
  },
  {
   "code": 7,
   "coordinates": {
    "ego": [
     0.198,
     -0.018000000000000002,
     0.1
    ],
    "end": [
     0.322,
     -0.05,
     0.1
    ]
   },
   "description": "Moving started ",
   "timestamp": "1689775472888419-2023-07-19-14:04:32:888.419",
   "x": 0.198,
   "y": -0.018000000000000002
  },
  {
   "code": 7,
   "coordinates": {
    "ego": [
     0.322,
     -0.05,
     0.1
    ],
    "end": [
     0.452,
     -0.098,
     0.1
    ]
   },
   "description": "Moving started ",
   "timestamp": "1689775472905275-2023-07-19-14:04:32:905.275",
   "x": 0.322,
   "y": -0.05
  },
  {
   "code": 7,
   "coordinates": {
    "ego": [
     0.452,
     -0.098,
     0.1
    ],
    "end": [
     0.5700000000000001,
     -0.14800000000000002,
     0.1
    ]
   },
   "description": "Moving started ",
   "timestamp": "1689775472905437-2023-07-19-14:04:32:905.437",
   "x": 0.452,
   "y": -0.098
  },
  {
   "code": 7,
   "coordinates": {
    "ego": [
     0.5700000000000001,
     -0.14800000000000002,
     0.1
    ],
    "end": [
     0.672,
     -0.2,
     0.1
    ]
   },
   "description": "Moving started ",
   "timestamp": "1689775472921740-2023-07-19-14:04:32:921.740",
   "x": 0.5700000000000001,
   "y": -0.14800000000000002
  },
  {
   "code": 7,
   "coordinates": {
    "ego": [
     0.672,
     -0.2,
     0.1
    ],
    "end": [
     0.776,
     -0.25,
     0.1
    ]
   },
   "description": "Moving started ",
   "timestamp": "1689775472921894-2023-07-19-14:04:32:921.894",
   "x": 0.672,
   "y": -0.2
  },
  {
   "code": 7,
   "coordinates": {
    "ego": [
     0.776,
     -0.25,
     0.1
    ],
    "end": [
     0.868,
     -0.292,
     0.1
    ]
   },
   "description": "Moving started ",
   "timestamp": "1689775472938430-2023-07-19-14:04:32:938.430",
   "x": 0.776,
   "y": -0.25
  },
  {
   "code": 7,
   "coordinates": {
    "ego": [
     0.868,
     -0.292,
     0.1
    ],
    "end": [
     0.952,
     -0.32599999999999996,
     0.1
    ]
   },
   "description": "Moving started ",
   "timestamp": "1689775472938580-2023-07-19-14:04:32:938.580",
   "x": 0.868,
   "y": -0.292
  },
  {
   "code": 7,
   "coordinates": {
    "ego": [
     0.952,
     -0.32599999999999996,
     0.1
    ],
    "end": [
     1.03,
     -0.356,
     0.1
    ]
   },
   "description": "Moving started ",
   "timestamp": "1689775472955215-2023-07-19-14:04:32:955.215",
   "x": 0.952,
   "y": -0.32599999999999996
  },
  {
   "code": 7,
   "coordinates": {
    "ego": [
     1.03,
     -0.356,
     0.1
    ],
    "end": [
     1.108,
     -0.376,
     0.1
    ]
   },
   "description": "Moving started ",
   "timestamp": "1689775472955388-2023-07-19-14:04:32:955.388",
   "x": 1.03,
   "y": -0.356
  },
  {
   "code": 7,
   "coordinates": {
    "ego": [
     1.108,
     -0.376,
     0.1
    ],
    "end": [
     1.1780000000000002,
     -0.388,
     0.1
    ]
   },
   "description": "Moving started ",
   "timestamp": "1689775472971958-2023-07-19-14:04:32:971.958",
   "x": 1.108,
   "y": -0.376
  },
  {
   "code": 7,
   "coordinates": {
    "ego": [
     1.1780000000000002,
     -0.388,
     0.1
    ],
    "end": [
     1.2400000000000002,
     -0.396,
     0.1
    ]
   },
   "description": "Moving started ",
   "timestamp": "1689775472972097-2023-07-19-14:04:32:972.97",
   "x": 1.1780000000000002,
   "y": -0.388
  },
  {
   "code": 7,
   "coordinates": {
    "ego": [
     1.1800000001783557,
     -0.3905594267526039,
     0.10000000000000005
    ],
    "end": [
     1.2380000001783558,
     -0.3905594267526039,
     0.10000000000000005
    ]
   },
   "description": "Moving started ",
   "timestamp": "1689775472972191-2023-07-19-14:04:32:972.191",
   "x": 1.1800000001783557,
   "y": -0.3905594267526039
  },
  {
   "code": 7,
   "coordinates": {
    "ego": [
     1.1800000001000002,
     -0.3905594267526039,
     0.10000000000000005
    ],
    "end": [
     1.2340000001000002,
     -0.3905594267526039,
     0.10000000000000005
    ]
   },
   "description": "Moving started ",
   "timestamp": "1689775472988757-2023-07-19-14:04:32:988.757",
   "x": 1.1800000001000002,
   "y": -0.3905594267526039
  },
  {
   "code": 7,
   "coordinates": {
    "ego": [
     1.1800000001000002,
     -0.3905594267526039,
     0.10000000000000005
    ],
    "end": [
     1.2340000001000002,
     -0.3745594267526039,
     0.10000000000000005
    ]
   },
   "description": "Moving started ",
   "timestamp": "1689775472988901-2023-07-19-14:04:32:988.901",
   "x": 1.1800000001000002,
   "y": -0.3905594267526039
  },
  {
   "code": 7,
   "coordinates": {
    "ego": [
     1.1800000000958797,
     -0.3877185434556902,
     0.10000000000000005
    ],
    "end": [
     1.2300000000958797,
     -0.36771854345569016,
     0.10000000000000005
    ]
   },
   "description": "Moving started ",
   "timestamp": "1689775473005117-2023-07-19-14:04:33:5.117",
   "x": 1.1800000000958797,
   "y": -0.3877185434556902
  },
  {
   "code": 7,
   "coordinates": {
    "ego": [
     1.180000000092848,
     -0.3840046366921491,
     0.10000000000000005
    ],
    "end": [
     1.232000000092848,
     -0.3600046366921491,
     0.10000000000000005
    ]
   },
   "description": "Moving started ",
   "timestamp": "1689775473005249-2023-07-19-14:04:33:5.249",
   "x": 1.180000000092848,
   "y": -0.3840046366921491
  },
  {
   "code": 7,
   "coordinates": {
    "ego": [
     1.1800000000907962,
     -0.3798140549175317,
     0.10000000000000005
    ],
    "end": [
     1.2280000000907962,
     -0.36381405491753166,
     0.10000000000000005
    ]
   },
   "description": "Moving started ",
   "timestamp": "1689775473021825-2023-07-19-14:04:33:21.825",
   "x": 1.1800000000907962,
   "y": -0.3798140549175317
  },
  {
   "code": 7,
   "coordinates": {
    "ego": [
     1.1800000000948683,
     -0.3766517772573633,
     0.10000000000000005
    ],
    "end": [
     1.2260000000948683,
     -0.3526517772573633,
     0.10000000000000005
    ]
   },
   "description": "Moving started ",
   "timestamp": "1689775473021957-2023-07-19-14:04:33:21.957",
   "x": 1.1800000000948683,
   "y": -0.3766517772573633
  },
  {
   "code": 7,
   "coordinates": {
    "ego": [
     1.1800000000886586,
     -0.3720261171904131,
     0.10000000000000006
    ],
    "end": [
     1.2280000000886586,
     -0.3520261171904131,
     0.10000000000000006
    ]
   },
   "description": "Moving started ",
   "timestamp": "1689775473038431-2023-07-19-14:04:33:38.431",
   "x": 1.1800000000886586,
   "y": -0.3720261171904131
  },
  {
   "code": 7,
   "coordinates": {
    "ego": [
     1.1801145298045748,
     -0.36738109455924145,
     0.10000000000000005
    ],
    "end": [
     1.2261145298045748,
     -0.34738109455924143,
     0.10000000000000005
    ]
   },
   "description": "Moving started ",
   "timestamp": "1689775473038551-2023-07-19-14:04:33:38.551",
   "x": 1.1801145298045748,
   "y": -0.36738109455924145
  },
  {
   "code": 7,
   "coordinates": {
    "ego": [
     1.181052049056838,
     -0.36175619197958253,
     0.10000000000000007
    ],
    "end": [
     1.223052049056838,
     -0.3457561919795825,
     0.10000000000000007
    ]
   },
   "description": "Moving started ",
   "timestamp": "1689775473055097-2023-07-19-14:04:33:55.97",
   "x": 1.181052049056838,
   "y": -0.36175619197958253
  },
  {
   "code": 7,
   "coordinates": {
    "ego": [
     1.1820888526631714,
     -0.3565437005720115,
     0.10000000000000013
    ],
    "end": [
     1.2220888526631715,
     -0.3385437005720115,
     0.10000000000000013
    ]
   },
   "description": "Moving started ",
   "timestamp": "1689775473055228-2023-07-19-14:04:33:55.228",
   "x": 1.1820888526631714,
   "y": -0.3565437005720115
  },
  {
   "code": 7,
   "coordinates": {
    "ego": [
     1.183221096802842,
     -0.35085138542661237,
     0.10000000000000027
    ],
    "end": [
     1.217221096802842,
     -0.33485138542661236,
     0.10000000000000027
    ]
   },
   "description": "Moving started ",
   "timestamp": "1689775473071791-2023-07-19-14:04:33:71.791",
   "x": 1.183221096802842,
   "y": -0.35085138542661237
  },
  {
   "code": 7,
   "coordinates": {
    "ego": [
     1.1843801656009736,
     -0.3450242103242348,
     0.10000000000000021
    ],
    "end": [
     1.2143801656009736,
     -0.3310242103242348,
     0.10000000000000021
    ]
   },
   "description": "Moving started ",
   "timestamp": "1689775473071961-2023-07-19-14:04:33:71.961",
   "x": 1.1843801656009736,
   "y": -0.3450242103242348
  },
  {
   "code": 7,
   "coordinates": {
    "ego": [
     1.1855341827601833,
     -0.33922243215397463,
     0.10000000000000026
    ],
    "end": [
     1.2155341827601833,
     -0.3232224321539746,
     0.10000000000000026
    ]
   },
   "description": "Moving started ",
   "timestamp": "1689775473088525-2023-07-19-14:04:33:88.525",
   "x": 1.1855341827601833,
   "y": -0.33922243215397463
  },
  {
   "code": 7,
   "coordinates": {
    "ego": [
     1.1867704037469498,
     -0.3330073772928407,
     0.10000000000000019
    ],
    "end": [
     1.2147704037469498,
     -0.3210073772928407,
     0.10000000000000019
    ]
   },
   "description": "Moving started ",
   "timestamp": "1689775473088656-2023-07-19-14:04:33:88.656",
   "x": 1.1867704037469498,
   "y": -0.3330073772928407
  },
  {
   "code": 7,
   "coordinates": {
    "ego": [
     1.1878739308979682,
     -0.32745943577840414,
     0.10000000000000017
    ],
    "end": [
     1.2138739308979682,
     -0.31745943577840413,
     0.10000000000000017
    ]
   },
   "description": "Moving started ",
   "timestamp": "1689775473105120-2023-07-19-14:04:33:105.120",
   "x": 1.1878739308979682,
   "y": -0.32745943577840414
  },
  {
   "code": 7,
   "coordinates": {
    "ego": [
     1.1889160088617365,
     -0.3222204277425181,
     0.10000000000000016
    ],
    "end": [
     1.2089160088617366,
     -0.31222042774251807,
     0.10000000000000016
    ]
   },
   "description": "Moving started ",
   "timestamp": "1689775473105251-2023-07-19-14:04:33:105.251",
   "x": 1.1889160088617365,
   "y": -0.3222204277425181
  },
  {
   "code": 7,
   "coordinates": {
    "ego": [
     1.190112100692743,
     -0.3162071207017069,
     0.10000000000000035
    ],
    "end": [
     1.212112100692743,
     -0.3082071207017069,
     0.10000000000000035
    ]
   },
   "description": "Moving started ",
   "timestamp": "1689775473121739-2023-07-19-14:04:33:121.739",
   "x": 1.190112100692743,
   "y": -0.3162071207017069
  },
  {
   "code": 7,
   "coordinates": {
    "ego": [
     1.1911236536567262,
     -0.31112157598501117,
     0.10000000000000027
    ],
    "end": [
     1.2061236536567261,
     -0.30512157598501116,
     0.10000000000000027
    ]
   },
   "description": "Moving started ",
   "timestamp": "1689775473121870-2023-07-19-14:04:33:121.870",
   "x": 1.1911236536567262,
   "y": -0.31112157598501117
  },
  {
   "code": 7,
   "coordinates": {
    "ego": [
     1.1921876266088767,
     -0.3057724916934162,
     0.10000000000000045
    ],
    "end": [
     1.2011876266088766,
     -0.3007724916934162,
     0.10000000000000045
    ]
   },
   "description": "Moving started ",
   "timestamp": "1689775473138412-2023-07-19-14:04:33:138.412",
   "x": 1.1921876266088767,
   "y": -0.3057724916934162
  },
  {
   "code": 7,
   "coordinates": {
    "ego": [
     1.1940401137331584,
     -0.2983691565314991,
     0.10000000000000044
    ],
    "end": [
     1.2010401137331583,
     -0.2953691565314991,
     0.10000000000000044
    ]
   },
   "description": "Moving started ",
   "timestamp": "1689775473138542-2023-07-19-14:04:33:138.542",
   "x": 1.1940401137331584,
   "y": -0.2983691565314991
  },
  {
   "code": 7,
   "coordinates": {
    "ego": [
     1.1968423173368472,
     -0.29270755186931385,
     0.10000000000000044
    ],
    "end": [
     1.199842317336847,
     -0.29070755186931385,
     0.10000000000000044
    ]
   },
   "description": "Moving started ",
   "timestamp": "1689775473155106-2023-07-19-14:04:33:155.106",
   "x": 1.1968423173368472,
   "y": -0.29270755186931385
  },
  {
   "code": 7,
   "coordinates": {
    "ego": [
     1.1986849798354065,
     -0.2899342588449339,
     0.10000000000000044
    ],
    "end": [
     1.2006849798354065,
     -0.2889342588449339,
     0.10000000000000044
    ]
   },
   "description": "Moving started ",
   "timestamp": "1689775473155236-2023-07-19-14:04:33:155.236",
   "x": 1.1986849798354065,
   "y": -0.2899342588449339
  },
  {
   "code": 7,
   "coordinates": {
    "ego": [
     1.1997642159535329,
     -0.28831903615832133,
     0.10000000000000044
    ],
    "end": [
     1.1957642159535329,
     -0.28831903615832133,
     0.10000000000000044
    ]
   },
   "description": "Moving started ",
   "timestamp": "1689775473474158-2023-07-19-14:04:33:474.158",
   "x": 1.1997642159535329,
   "y": -0.28831903615832133
  },
  {
   "code": 7,
   "coordinates": {
    "ego": [
     1.1957642159535329,
     -0.28831903615832133,
     0.10000000000000044
    ],
    "end": [
     1.1857642159535329,
     -0.29131903615832133,
     0.10000000000000044
    ]
   },
   "description": "Moving started ",
   "timestamp": "1689775473483952-2023-07-19-14:04:33:483.952",
   "x": 1.1957642159535329,
   "y": -0.28831903615832133
  },
  {
   "code": 7,
   "coordinates": {
    "ego": [
     1.1857642159535329,
     -0.29131903615832133,
     0.10000000000000044
    ],
    "end": [
     1.168764215953533,
     -0.30431903615832134,
     0.10000000000000044
    ]
   },
   "description": "Moving started ",
   "timestamp": "1689775473493901-2023-07-19-14:04:33:493.901",
   "x": 1.1857642159535329,
   "y": -0.29131903615832133
  },
  {
   "code": 7,
   "coordinates": {
    "ego": [
     1.168764215953533,
     -0.30431903615832134,
     0.10000000000000044
    ],
    "end": [
     1.150764215953533,
     -0.31831903615832136,
     0.10000000000000044
    ]
   },
   "description": "Moving started ",
   "timestamp": "1689775473494337-2023-07-19-14:04:33:494.337",
   "x": 1.168764215953533,
   "y": -0.30431903615832134
  },
  {
   "code": 7,
   "coordinates": {
    "ego": [
     1.150764215953533,
     -0.31831903615832136,
     0.10000000000000044
    ],
    "end": [
     1.138764215953533,
     -0.32731903615832136,
     0.10000000000000044
    ]
   },
   "description": "Moving started ",
   "timestamp": "1689775473509283-2023-07-19-14:04:33:509.283",
   "x": 1.150764215953533,
   "y": -0.31831903615832136
  },
  {
   "code": 7,
   "coordinates": {
    "ego": [
     1.138764215953533,
     -0.32731903615832136,
     0.10000000000000044
    ],
    "end": [
     1.136764215953533,
     -0.32931903615832137,
     0.10000000000000044
    ]
   },
   "description": "Moving started ",
   "timestamp": "1689775473509515-2023-07-19-14:04:33:509.515",
   "x": 1.138764215953533,
   "y": -0.32731903615832136
  },
  {
   "code": 7,
   "coordinates": {
    "ego": [
     1.136764215953533,
     -0.32931903615832137,
     0.10000000000000044
    ],
    "end": [
     1.134764215953533,
     -0.33131903615832137,
     0.10000000000000044
    ]
   },
   "description": "Moving started ",
   "timestamp": "1689775473522812-2023-07-19-14:04:33:522.812",
   "x": 1.136764215953533,
   "y": -0.32931903615832137
  },
  {
   "code": 1,
   "coordinates": {
    "ego": [
     1.134764215953533,
     -0.33131903615832137,
     0.10000000000000044
    ]
   },
   "description": "Left click",
   "timestamp": "1689775473571714-2023-07-19-14:04:33:571.714",
   "x": 1.134764215953533,
   "y": -0.33131903615832137
  },
  {
   "code": 3,
   "coordinates": {
    "box1": [
     1.5,
     -0.5,
     0.151
    ],
    "ego": [
     1.134764215953533,
     -0.33131903615832137,
     0.10000000000000044
    ]
   },
   "description": "Attach box1",
   "timestamp": "1689775473571749-2023-07-19-14:04:33:571.749",
   "x": 1.134764215953533,
   "y": -0.33131903615832137
  },
  {
   "code": 7,
   "coordinates": {
    "ego": [
     1.134764215953533,
     -0.33131903615832137,
     0.10000000000000044
    ],
    "end": [
     1.132764215953533,
     -0.32731903615832136,
     0.10000000000000044
    ]
   },
   "description": "Moving started ",
   "timestamp": "1689775473643977-2023-07-19-14:04:33:643.977",
   "x": 1.134764215953533,
   "y": -0.33131903615832137
  },
  {
   "code": 7,
   "coordinates": {
    "ego": [
     1.132764215953533,
     -0.32731903615832136,
     0.10000000000000044
    ],
    "end": [
     1.124764215953533,
     -0.31631903615832135,
     0.10000000000000044
    ]
   },
   "description": "Moving started ",
   "timestamp": "1689775473677720-2023-07-19-14:04:33:677.720",
   "x": 1.132764215953533,
   "y": -0.32731903615832136
  },
  {
   "code": 7,
   "coordinates": {
    "ego": [
     1.124764215953533,
     -0.31631903615832135,
     0.10000000000000044
    ],
    "end": [
     1.106764215953533,
     -0.29631903615832134,
     0.10000000000000044
    ]
   },
   "description": "Moving started ",
   "timestamp": "1689775473678062-2023-07-19-14:04:33:678.62",
   "x": 1.124764215953533,
   "y": -0.31631903615832135
  },
  {
   "code": 7,
   "coordinates": {
    "ego": [
     1.106764215953533,
     -0.29631903615832134,
     0.10000000000000044
    ],
    "end": [
     1.086764215953533,
     -0.2743190361583213,
     0.10000000000000044
    ]
   },
   "description": "Moving started ",
   "timestamp": "1689775473678389-2023-07-19-14:04:33:678.389",
   "x": 1.106764215953533,
   "y": -0.29631903615832134
  },
  {
   "code": 7,
   "coordinates": {
    "ego": [
     1.086764215953533,
     -0.2743190361583213,
     0.10000000000000044
    ],
    "end": [
     1.0547642159535329,
     -0.24831903615832132,
     0.10000000000000044
    ]
   },
   "description": "Moving started ",
   "timestamp": "1689775473678701-2023-07-19-14:04:33:678.701",
   "x": 1.086764215953533,
   "y": -0.2743190361583213
  },
  {
   "code": 7,
   "coordinates": {
    "ego": [
     1.0547642159535329,
     -0.24831903615832132,
     0.10000000000000044
    ],
    "end": [
     1.0267642159535328,
     -0.22431903615832133,
     0.10000000000000044
    ]
   },
   "description": "Moving started ",
   "timestamp": "1689775473693891-2023-07-19-14:04:33:693.891",
   "x": 1.0547642159535329,
   "y": -0.24831903615832132
  },
  {
   "code": 7,
   "coordinates": {
    "ego": [
     1.0267642159535328,
     -0.22431903615832133,
     0.10000000000000044
    ],
    "end": [
     0.9947642159535328,
     -0.19831903615832133,
     0.10000000000000044
    ]
   },
   "description": "Moving started ",
   "timestamp": "1689775473694293-2023-07-19-14:04:33:694.293",
   "x": 1.0267642159535328,
   "y": -0.22431903615832133
  },
  {
   "code": 7,
   "coordinates": {
    "ego": [
     0.9947642159535328,
     -0.19831903615832133,
     0.10000000000000044
    ],
    "end": [
     0.9567642159535328,
     -0.17231903615832134,
     0.10000000000000044
    ]
   },
   "description": "Moving started ",
   "timestamp": "1689775473708958-2023-07-19-14:04:33:708.958",
   "x": 0.9947642159535328,
   "y": -0.19831903615832133
  },
  {
   "code": 7,
   "coordinates": {
    "ego": [
     0.9567642159535328,
     -0.17231903615832134,
     0.10000000000000044
    ],
    "end": [
     0.9187642159535327,
     -0.14431903615832134,
     0.10000000000000044
    ]
   },
   "description": "Moving started ",
   "timestamp": "1689775473709277-2023-07-19-14:04:33:709.277",
   "x": 0.9567642159535328,
   "y": -0.17231903615832134
  },
  {
   "code": 7,
   "coordinates": {
    "ego": [
     0.9187642159535327,
     -0.14431903615832134,
     0.10000000000000044
    ],
    "end": [
     0.8807642159535327,
     -0.11631903615832134,
     0.10000000000000044
    ]
   },
   "description": "Moving started ",
   "timestamp": "1689775473722737-2023-07-19-14:04:33:722.737",
   "x": 0.9187642159535327,
   "y": -0.14431903615832134
  },
  {
   "code": 7,
   "coordinates": {
    "ego": [
     0.8807642159535327,
     -0.11631903615832134,
     0.10000000000000044
    ],
    "end": [
     0.8467642159535327,
     -0.08631903615832134,
     0.10000000000000044
    ]
   },
   "description": "Moving started ",
   "timestamp": "1689775473738507-2023-07-19-14:04:33:738.507",
   "x": 0.8807642159535327,
   "y": -0.11631903615832134
  },
  {
   "code": 7,
   "coordinates": {
    "ego": [
     0.8467642159535327,
     -0.08631903615832134,
     0.10000000000000044
    ],
    "end": [
     0.8107642159535327,
     -0.05431903615832134,
     0.10000000000000044
    ]
   },
   "description": "Moving started ",
   "timestamp": "1689775473738607-2023-07-19-14:04:33:738.607",
   "x": 0.8467642159535327,
   "y": -0.08631903615832134
  },
  {
   "code": 7,
   "coordinates": {
    "ego": [
     0.8107642159535327,
     -0.05431903615832134,
     0.10000000000000044
    ],
    "end": [
     0.7707642159535326,
     -0.022319036158321343,
     0.10000000000000044
    ]
   },
   "description": "Moving started ",
   "timestamp": "1689775473755059-2023-07-19-14:04:33:755.59",
   "x": 0.8107642159535327,
   "y": -0.05431903615832134
  },
  {
   "code": 7,
   "coordinates": {
    "ego": [
     0.7707642159535326,
     -0.022319036158321343,
     0.10000000000000044
    ],
    "end": [
     0.7347642159535326,
     0.009680963841678658,
     0.10000000000000044
    ]
   },
   "description": "Moving started ",
   "timestamp": "1689775473755214-2023-07-19-14:04:33:755.214",
   "x": 0.7707642159535326,
   "y": -0.022319036158321343
  },
  {
   "code": 7,
   "coordinates": {
    "ego": [
     0.7347642159535326,
     0.009680963841678658,
     0.10000000000000044
    ],
    "end": [
     0.7007642159535326,
     0.04368096384167866,
     0.10000000000000044
    ]
   },
   "description": "Moving started ",
   "timestamp": "1689775473772092-2023-07-19-14:04:33:772.92",
   "x": 0.7347642159535326,
   "y": 0.009680963841678658
  },
  {
   "code": 7,
   "coordinates": {
    "ego": [
     0.7007642159535326,
     0.04368096384167866,
     0.10000000000000044
    ],
    "end": [
     0.6687642159535325,
     0.07768096384167866,
     0.10000000000000044
    ]
   },
   "description": "Moving started ",
   "timestamp": "1689775473772220-2023-07-19-14:04:33:772.220",
   "x": 0.7007642159535326,
   "y": 0.04368096384167866
  },
  {
   "code": 7,
   "coordinates": {
    "ego": [
     0.6687642159535325,
     0.07768096384167866,
     0.10000000000000044
    ],
    "end": [
     0.6347642159535325,
     0.11568096384167867,
     0.10000000000000044
    ]
   },
   "description": "Moving started ",
   "timestamp": "1689775473772290-2023-07-19-14:04:33:772.290",
   "x": 0.6687642159535325,
   "y": 0.07768096384167866
  },
  {
   "code": 7,
   "coordinates": {
    "ego": [
     0.6347642159535325,
     0.11568096384167867,
     0.10000000000000044
    ],
    "end": [
     0.6007642159535325,
     0.15368096384167867,
     0.10000000000000044
    ]
   },
   "description": "Moving started ",
   "timestamp": "1689775473788596-2023-07-19-14:04:33:788.596",
   "x": 0.6347642159535325,
   "y": 0.11568096384167867
  },
  {
   "code": 7,
   "coordinates": {
    "ego": [
     0.6007642159535325,
     0.15368096384167867,
     0.10000000000000044
    ],
    "end": [
     0.5687642159535324,
     0.19168096384167868,
     0.10000000000000044
    ]
   },
   "description": "Moving started ",
   "timestamp": "1689775473788726-2023-07-19-14:04:33:788.726",
   "x": 0.6007642159535325,
   "y": 0.15368096384167867
  },
  {
   "code": 7,
   "coordinates": {
    "ego": [
     0.5687642159535324,
     0.19168096384167868,
     0.10000000000000044
    ],
    "end": [
     0.5387642159535324,
     0.22768096384167869,
     0.10000000000000044
    ]
   },
   "description": "Moving started ",
   "timestamp": "1689775473805051-2023-07-19-14:04:33:805.51",
   "x": 0.5687642159535324,
   "y": 0.19168096384167868
  },
  {
   "code": 7,
   "coordinates": {
    "ego": [
     0.5387642159535324,
     0.22768096384167869,
     0.10000000000000044
    ],
    "end": [
     0.5087642159535324,
     0.2636809638416787,
     0.10000000000000044
    ]
   },
   "description": "Moving started ",
   "timestamp": "1689775473805177-2023-07-19-14:04:33:805.177",
   "x": 0.5387642159535324,
   "y": 0.22768096384167869
  },
  {
   "code": 7,
   "coordinates": {
    "ego": [
     0.5087642159535324,
     0.2636809638416787,
     0.10000000000000044
    ],
    "end": [
     0.4707642159535324,
     0.3036809638416787,
     0.10000000000000044
    ]
   },
   "description": "Moving started ",
   "timestamp": "1689775473821792-2023-07-19-14:04:33:821.792",
   "x": 0.5087642159535324,
   "y": 0.2636809638416787
  },
  {
   "code": 7,
   "coordinates": {
    "ego": [
     0.4707642159535324,
     0.3036809638416787,
     0.10000000000000044
    ],
    "end": [
     0.4307642159535324,
     0.3536809638416787,
     0.10000000000000044
    ]
   },
   "description": "Moving started ",
   "timestamp": "1689775473821915-2023-07-19-14:04:33:821.915",
   "x": 0.4707642159535324,
   "y": 0.3036809638416787
  },
  {
   "code": 7,
   "coordinates": {
    "ego": [
     0.4307642159535324,
     0.3536809638416787,
     0.10000000000000044
    ],
    "end": [
     0.38876421595353244,
     0.39568096384167867,
     0.10000000000000044
    ]
   },
   "description": "Moving started ",
   "timestamp": "1689775473838384-2023-07-19-14:04:33:838.384",
   "x": 0.4307642159535324,
   "y": 0.3536809638416787
  },
  {
   "code": 7,
   "coordinates": {
    "ego": [
     0.38876421595353244,
     0.39568096384167867,
     0.10000000000000044
    ],
    "end": [
     0.34676421595353246,
     0.44368096384167865,
     0.10000000000000044
    ]
   },
   "description": "Moving started ",
   "timestamp": "1689775473838513-2023-07-19-14:04:33:838.513",
   "x": 0.38876421595353244,
   "y": 0.39568096384167867
  },
  {
   "code": 7,
   "coordinates": {
    "ego": [
     0.34676421595353246,
     0.44368096384167865,
     0.10000000000000044
    ],
    "end": [
     0.3007642159535325,
     0.49368096384167864,
     0.10000000000000044
    ]
   },
   "description": "Moving started ",
   "timestamp": "1689775473855032-2023-07-19-14:04:33:855.32",
   "x": 0.34676421595353246,
   "y": 0.44368096384167865
  },
  {
   "code": 7,
   "coordinates": {
    "ego": [
     0.3007642159535325,
     0.49368096384167864,
     0.10000000000000044
    ],
    "end": [
     0.24476421595353248,
     0.5456809638416786,
     0.10000000000000044
    ]
   },
   "description": "Moving started ",
   "timestamp": "1689775473855159-2023-07-19-14:04:33:855.159",
   "x": 0.3007642159535325,
   "y": 0.49368096384167864
  },
  {
   "code": 7,
   "coordinates": {
    "ego": [
     0.24476421595353248,
     0.5456809638416786,
     0.10000000000000044
    ],
    "end": [
     0.1907642159535325,
     0.5976809638416787,
     0.10000000000000044
    ]
   },
   "description": "Moving started ",
   "timestamp": "1689775473871765-2023-07-19-14:04:33:871.765",
   "x": 0.24476421595353248,
   "y": 0.5456809638416786
  },
  {
   "code": 7,
   "coordinates": {
    "ego": [
     0.1907642159535325,
     0.5976809638416787,
     0.10000000000000044
    ],
    "end": [
     0.1407642159535325,
     0.6516809638416787,
     0.10000000000000044
    ]
   },
   "description": "Moving started ",
   "timestamp": "1689775473871947-2023-07-19-14:04:33:871.947",
   "x": 0.1907642159535325,
   "y": 0.5976809638416787
  },
  {
   "code": 7,
   "coordinates": {
    "ego": [
     0.1407642159535325,
     0.6516809638416787,
     0.10000000000000044
    ],
    "end": [
     0.0907642159535325,
     0.7076809638416788,
     0.10000000000000044
    ]
   },
   "description": "Moving started ",
   "timestamp": "1689775473888417-2023-07-19-14:04:33:888.417",
   "x": 0.1407642159535325,
   "y": 0.6516809638416787
  },
  {
   "code": 7,
   "coordinates": {
    "ego": [
     0.0907642159535325,
     0.7076809638416788,
     0.10000000000000044
    ],
    "end": [
     0.0367642159535325,
     0.7656809638416788,
     0.10000000000000044
    ]
   },
   "description": "Moving started ",
   "timestamp": "1689775473888540-2023-07-19-14:04:33:888.540",
   "x": 0.0907642159535325,
   "y": 0.7076809638416788
  },
  {
   "code": 7,
   "coordinates": {
    "ego": [
     0.0367642159535325,
     0.7656809638416788,
     0.10000000000000044
    ],
    "end": [
     -0.0232357840464675,
     0.8256809638416789,
     0.10000000000000044
    ]
   },
   "description": "Moving started ",
   "timestamp": "1689775473905063-2023-07-19-14:04:33:905.63",
   "x": 0.0367642159535325,
   "y": 0.7656809638416788
  },
  {
   "code": 7,
   "coordinates": {
    "ego": [
     -0.0232357840464675,
     0.8256809638416789,
     0.10000000000000044
    ],
    "end": [
     -0.0652357840464675,
     0.8856809638416789,
     0.10000000000000044
    ]
   },
   "description": "Moving started ",
   "timestamp": "1689775473905196-2023-07-19-14:04:33:905.196",
   "x": -0.0232357840464675,
   "y": 0.8256809638416789
  },
  {
   "code": 7,
   "coordinates": {
    "ego": [
     -0.0652357840464675,
     0.8856809638416789,
     0.10000000000000044
    ],
    "end": [
     -0.12323578404646751,
     0.941680963841679,
     0.10000000000000044
    ]
   },
   "description": "Moving started ",
   "timestamp": "1689775473921716-2023-07-19-14:04:33:921.716",
   "x": -0.0652357840464675,
   "y": 0.8856809638416789
  },
  {
   "code": 7,
   "coordinates": {
    "ego": [
     -0.12323578404646751,
     0.941680963841679,
     0.10000000000000044
    ],
    "end": [
     -0.1832357840464675,
     1.001680963841679,
     0.10000000000000044
    ]
   },
   "description": "Moving started ",
   "timestamp": "1689775473921855-2023-07-19-14:04:33:921.855",
   "x": -0.12323578404646751,
   "y": 0.941680963841679
  },
  {
   "code": 7,
   "coordinates": {
    "ego": [
     -0.1832357840464675,
     1.001680963841679,
     0.10000000000000044
    ],
    "end": [
     -0.2412357840464675,
     1.061680963841679,
     0.10000000000000044
    ]
   },
   "description": "Moving started ",
   "timestamp": "1689775473938362-2023-07-19-14:04:33:938.362",
   "x": -0.1832357840464675,
   "y": 1.001680963841679
  },
  {
   "code": 7,
   "coordinates": {
    "ego": [
     -0.2412357840464675,
     1.061680963841679,
     0.10000000000000044
    ],
    "end": [
     -0.2992357840464675,
     1.1176809638416791,
     0.10000000000000044
    ]
   },
   "description": "Moving started ",
   "timestamp": "1689775473938513-2023-07-19-14:04:33:938.513",
   "x": -0.2412357840464675,
   "y": 1.061680963841679
  },
  {
   "code": 7,
   "coordinates": {
    "ego": [
     -0.2992357840464675,
     1.1176809638416791,
     0.10000000000000044
    ],
    "end": [
     -0.3512357840464675,
     1.1776809638416792,
     0.10000000000000044
    ]
   },
   "description": "Moving started ",
   "timestamp": "1689775473955044-2023-07-19-14:04:33:955.44",
   "x": -0.2992357840464675,
   "y": 1.1176809638416791
  },
  {
   "code": 7,
   "coordinates": {
    "ego": [
     -0.3512357840464675,
     1.1776809638416792,
     0.10000000000000044
    ],
    "end": [
     -0.4032357840464675,
     1.2356809638416792,
     0.10000000000000044
    ]
   },
   "description": "Moving started ",
   "timestamp": "1689775473955200-2023-07-19-14:04:33:955.200",
   "x": -0.3512357840464675,
   "y": 1.1776809638416792
  },
  {
   "code": 7,
   "coordinates": {
    "ego": [
     -0.4032357840464675,
     1.2356809638416792,
     0.10000000000000044
    ],
    "end": [
     -0.45123578404646747,
     1.2936809638416793,
     0.10000000000000044
    ]
   },
   "description": "Moving started ",
   "timestamp": "1689775473972039-2023-07-19-14:04:33:972.39",
   "x": -0.4032357840464675,
   "y": 1.2356809638416792
  },
  {
   "code": 7,
   "coordinates": {
    "ego": [
     -0.45123578404646747,
     1.2936809638416793,
     0.10000000000000044
    ],
    "end": [
     -0.5012357840464675,
     1.3436809638416793,
     0.10000000000000044
    ]
   },
   "description": "Moving started ",
   "timestamp": "1689775473972150-2023-07-19-14:04:33:972.150",
   "x": -0.45123578404646747,
   "y": 1.2936809638416793
  },
  {
   "code": 7,
   "coordinates": {
    "ego": [
     -0.5012357840464675,
     1.3436809638416793,
     0.10000000000000044
    ],
    "end": [
     -0.5452357840464676,
     1.3936809638416794,
     0.10000000000000044
    ]
   },
   "description": "Moving started ",
   "timestamp": "1689775473972246-2023-07-19-14:04:33:972.246",
   "x": -0.5012357840464675,
   "y": 1.3436809638416793
  },
  {
   "code": 7,
   "coordinates": {
    "ego": [
     -0.5452357840464676,
     1.3936809638416794,
     0.10000000000000044
    ],
    "end": [
     -0.5852357840464676,
     1.4376809638416794,
     0.10000000000000044
    ]
   },
   "description": "Moving started ",
   "timestamp": "1689775473988667-2023-07-19-14:04:33:988.667",
   "x": -0.5452357840464676,
   "y": 1.3936809638416794
  },
  {
   "code": 7,
   "coordinates": {
    "ego": [
     -0.5852357840464676,
     1.4376809638416794,
     0.10000000000000044
    ],
    "end": [
     -0.6232357840464676,
     1.4816809638416795,
     0.10000000000000044
    ]
   },
   "description": "Moving started ",
   "timestamp": "1689775473988795-2023-07-19-14:04:33:988.795",
   "x": -0.5852357840464676,
   "y": 1.4376809638416794
  },
  {
   "code": 7,
   "coordinates": {
    "ego": [
     -0.6232357840464676,
     1.4816809638416795,
     0.10000000000000044
    ],
    "end": [
     -0.6532357840464676,
     1.5136809638416795,
     0.10000000000000044
    ]
   },
   "description": "Moving started ",
   "timestamp": "1689775474005059-2023-07-19-14:04:34:5.59",
   "x": -0.6232357840464676,
   "y": 1.4816809638416795
  },
  {
   "code": 7,
   "coordinates": {
    "ego": [
     -0.6532357840464676,
     1.5136809638416795,
     0.10000000000000044
    ],
    "end": [
     -0.6812357840464677,
     1.5416809638416795,
     0.10000000000000044
    ]
   },
   "description": "Moving started ",
   "timestamp": "1689775474005183-2023-07-19-14:04:34:5.183",
   "x": -0.6532357840464676,
   "y": 1.5136809638416795
  },
  {
   "code": 7,
   "coordinates": {
    "ego": [
     -0.6812357840464677,
     1.5416809638416795,
     0.10000000000000044
    ],
    "end": [
     -0.6992357840464677,
     1.5636809638416795,
     0.10000000000000044
    ]
   },
   "description": "Moving started ",
   "timestamp": "1689775474021833-2023-07-19-14:04:34:21.833",
   "x": -0.6812357840464677,
   "y": 1.5416809638416795
  },
  {
   "code": 7,
   "coordinates": {
    "ego": [
     -0.6992357840464677,
     1.5636809638416795,
     0.10000000000000044
    ],
    "end": [
     -0.7112357840464677,
     1.5776809638416796,
     0.10000000000000044
    ]
   },
   "description": "Moving started ",
   "timestamp": "1689775474021948-2023-07-19-14:04:34:21.948",
   "x": -0.6992357840464677,
   "y": 1.5636809638416795
  },
  {
   "code": 7,
   "coordinates": {
    "ego": [
     -0.7112357840464677,
     1.5776809638416796,
     0.10000000000000044
    ],
    "end": [
     -0.7162357840464677,
     1.5856809638416796,
     0.10000000000000044
    ]
   },
   "description": "Moving started ",
   "timestamp": "1689775474038377-2023-07-19-14:04:34:38.377",
   "x": -0.7112357840464677,
   "y": 1.5776809638416796
  },
  {
   "code": 7,
   "coordinates": {
    "ego": [
     -0.7162357840464677,
     1.5856809638416796,
     0.10000000000000044
    ],
    "end": [
     -0.7192357840464677,
     1.5896809638416796,
     0.10000000000000044
    ]
   },
   "description": "Moving started ",
   "timestamp": "1689775474038451-2023-07-19-14:04:34:38.451",
   "x": -0.7162357840464677,
   "y": 1.5856809638416796
  },
  {
   "code": 4,
   "coordinates": {
    "box1": [
     -0.35400000000000065,
     1.421000000000001,
     0.151
    ],
    "ego": [
     -0.7192357840464677,
     1.5896809638416796,
     0.10000000000000044
    ]
   },
   "description": "Release box1",
   "timestamp": "1689775474221669-2023-07-19-14:04:34:221.669",
   "x": -0.7192357840464677,
   "y": 1.5896809638416796
  },
  {
   "code": 7,
   "coordinates": {
    "ego": [
     -0.7192357840464677,
     1.5896809638416796,
     0.10000000000000044
    ],
    "end": [
     -0.7202357840464677,
     1.5906809638416795,
     0.10000000000000044
    ]
   },
   "description": "Moving started ",
   "timestamp": "1689775474221706-2023-07-19-14:04:34:221.706",
   "x": -0.7192357840464677,
   "y": 1.5896809638416796
  },
  {
   "code": 7,
   "coordinates": {
    "ego": [
     -0.7202357840464677,
     1.5906809638416795,
     0.10000000000000044
    ],
    "end": [
     -0.7232357840464677,
     1.5906809638416795,
     0.10000000000000044
    ]
   },
   "description": "Moving started ",
   "timestamp": "1689775474221788-2023-07-19-14:04:34:221.788",
   "x": -0.7202357840464677,
   "y": 1.5906809638416795
  },
  {
   "code": 7,
   "coordinates": {
    "ego": [
     -0.7232357840464677,
     1.5906809638416795,
     0.10000000000000044
    ],
    "end": [
     -0.7272357840464677,
     1.5906809638416795,
     0.10000000000000044
    ]
   },
   "description": "Moving started ",
   "timestamp": "1689775474221835-2023-07-19-14:04:34:221.835",
   "x": -0.7232357840464677,
   "y": 1.5906809638416795
  },
  {
   "code": 7,
   "coordinates": {
    "ego": [
     -0.7272357840464677,
     1.5906809638416795,
     0.10000000000000044
    ],
    "end": [
     -0.7282357840464677,
     1.5906809638416795,
     0.10000000000000044
    ]
   },
   "description": "Moving started ",
   "timestamp": "1689775474221881-2023-07-19-14:04:34:221.881",
   "x": -0.7272357840464677,
   "y": 1.5906809638416795
  },
  {
   "code": 7,
   "coordinates": {
    "ego": [
     -0.7282357840464677,
     1.5906809638416795,
     0.10000000000000044
    ],
    "end": [
     -0.7302357840464677,
     1.5906809638416795,
     0.10000000000000044
    ]
   },
   "description": "Moving started ",
   "timestamp": "1689775474221925-2023-07-19-14:04:34:221.925",
   "x": -0.7282357840464677,
   "y": 1.5906809638416795
  },
  {
   "code": 7,
   "coordinates": {
    "ego": [
     -0.7302357840464677,
     1.5906809638416795,
     0.10000000000000044
    ],
    "end": [
     -0.7322357840464677,
     1.5906809638416795,
     0.10000000000000044
    ]
   },
   "description": "Moving started ",
   "timestamp": "1689775474221969-2023-07-19-14:04:34:221.969",
   "x": -0.7302357840464677,
   "y": 1.5906809638416795
  }
 ],
 "participantID": "65",
 "puzzle-file": "../../scenes-30a/0-1-1-pnp.g",
 "rating": 1,
 "run": 2,
 "solved": true,
 "start-time": "1689775471760364-2023-07-19-14:04:31:760.364",
 "time-solved": 2.180146877,
 "total-time": 3.670262067
}
